Metadata-Version: 2.1
Name: epochraft
Version: 0.1.0.dev20231107
Summary: Supercharge Your LLM Training with Checkpointable Data Loading
Author: Takuya Akiba
Author-email: takuya.akiba@stability.ai
License: MIT License
Project-URL: repository, https://github.com/iwiwi/epochraft
Classifier: Development Status :: 2 - Pre-Alpha
Classifier: Intended Audience :: Science/Research
Classifier: Intended Audience :: Developers
Classifier: License :: OSI Approved :: MIT License
Classifier: Programming Language :: Python :: 3
Classifier: Programming Language :: Python :: 3.8
Classifier: Programming Language :: Python :: 3.9
Classifier: Programming Language :: Python :: 3.10
Classifier: Programming Language :: Python :: 3.11
Classifier: Programming Language :: Python :: 3 :: Only
Classifier: Topic :: Scientific/Engineering
Classifier: Topic :: Scientific/Engineering :: Mathematics
Classifier: Topic :: Scientific/Engineering :: Artificial Intelligence
Classifier: Topic :: Software Development
Classifier: Topic :: Software Development :: Libraries
Classifier: Topic :: Software Development :: Libraries :: Python Modules
Requires-Python: >=3.8
License-File: LICENSE
Requires-Dist: torch
Requires-Dist: numpy
Requires-Dist: braceexpand
Requires-Dist: smart-open
Provides-Extra: development
Requires-Dist: black ; extra == 'development'
Requires-Dist: blackdoc ; extra == 'development'
Requires-Dist: flake8 ; extra == 'development'
Requires-Dist: isort ; extra == 'development'
Requires-Dist: mypy ; extra == 'development'
Requires-Dist: pytest ; extra == 'development'
Requires-Dist: mosaicml-streaming ; extra == 'development'
Requires-Dist: transformers ; extra == 'development'
Requires-Dist: sentencepiece ; extra == 'development'
Requires-Dist: cbor2 ; extra == 'development'
